LICENSE
MANIFEST.in
README.md
setup.py
ToMd5.egg-info/PKG-INFO
ToMd5.egg-info/SOURCES.txt
ToMd5.egg-info/dependency_links.txt
ToMd5.egg-info/top_level.txt
mycode/__init__.py
mycode/__version__.py
mycode/base64.py
mycode/core.py
mycode/hashlib.py
mycode/pyDes.py